mlrb_agent_tasks/__init__.py
mlrb_agent_tasks/prompt_template.j2
mlrb_agent_tasks/prompts.py
mlrb_agent_tasks/run.py
mlrb_agent_tasks/full_benchmark/baby_lm/README.md
mlrb_agent_tasks/full_benchmark/budget_model_inference/README.md
mlrb_agent_tasks/full_benchmark/budget_model_training/README.md
mlrb_agent_tasks/full_benchmark/edge_llm_compression/README.md
mlrb_agent_tasks/full_benchmark/edge_llm_training/README.md
mlrb_agent_tasks/full_benchmark/llm_efficiency/README.md
mlrb_agent_tasks/full_benchmark/llm_merging/README.md
mlrb_agent_tasks/full_benchmark/llm_merging/data.py
mlrb_agent_tasks/full_benchmark/llm_merging/evaluation.py
mlrb_agent_tasks/full_benchmark/llm_merging/main.py
mlrb_agent_tasks/full_benchmark/llm_merging/setup.py
mlrb_agent_tasks/full_benchmark/llm_merging/merging/FlanT5Avg.py
mlrb_agent_tasks/full_benchmark/llm_merging/merging/LlamaAvg.py
mlrb_agent_tasks/full_benchmark/llm_merging/merging/Merges.py
mlrb_agent_tasks/full_benchmark/llm_merging/merging/__init__.py
mlrb_agent_tasks/full_benchmark/llm_merging/model/__init__.py
mlrb_agent_tasks/full_benchmark/llm_merging/model/decoder_functions.py
mlrb_agent_tasks/full_benchmark/llm_merging/model/encoder_decoder_functions.py
mlrb_agent_tasks/full_benchmark/math_reasoning/example.py
mlrb_agent_tasks/full_benchmark/mini_pile/README.md
mlrb_agent_tasks/mini_benchmark/mini_baby_lm/README.md
mlrb_agent_tasks/mini_benchmark/mini_baby_lm/example.py
mlrb_agent_tasks/mini_benchmark/mini_budget_model_inference/README.md
mlrb_agent_tasks/mini_benchmark/mini_budget_model_inference/example.py
mlrb_agent_tasks/mini_benchmark/mini_budget_model_training/README.md
mlrb_agent_tasks/mini_benchmark/mini_budget_model_training/example.py
mlrb_agent_tasks/mini_benchmark/mini_edge_llm_compression/README.md
mlrb_agent_tasks/mini_benchmark/mini_edge_llm_compression/example.py
mlrb_agent_tasks/mini_benchmark/mini_edge_llm_training/README.md
mlrb_agent_tasks/mini_benchmark/mini_edge_llm_training/example.py
mlrb_agent_tasks-0.0.23.dist-info/LICENSE
mlrb_agent_tasks-0.0.23.dist-info/METADATA
mlrb_agent_tasks-0.0.23.dist-info/WHEEL
mlrb_agent_tasks-0.0.23.dist-info/entry_points.txt
mlrb_agent_tasks-0.0.23.dist-info/top_level.txt
mlrb_agent_tasks-0.0.23.dist-info/RECORD
