Metadata-Version: 2.1
Name: mlrb-agent-tasks
Version: 0.0.23
Summary: A task package for ML Research Bench
Home-page: http://github.com/AlgorithmicResearchGroup/agent-tasks
Author: Algorithmic Research Group
Author-email: matt@algorithmicresearchgroup.com
Keywords: tasks,agent,benchmark
License-File: LICENSE
Requires-Dist: Jinja2==3.1.4
Requires-Dist: MarkupSafe==2.1.5
